README
setup.cfg
setup.py
eVotUM/__init__.py
eVotUM/Cripto/__init__.py
eVotUM/Cripto/auditlogs.py
eVotUM/Cripto/cautils.py
eVotUM/Cripto/eccblind.py
eVotUM/Cripto/hashfunctions.py
eVotUM/Cripto/jose.py
eVotUM/Cripto/pbkdf2.py
eVotUM/Cripto/pkiutils.py
eVotUM/Cripto/shamirsecret.py
eVotUM/Cripto/utils.py
evotum_cripto.egg-info/PKG-INFO
evotum_cripto.egg-info/SOURCES.txt
evotum_cripto.egg-info/dependency_links.txt
evotum_cripto.egg-info/requires.txt
evotum_cripto.egg-info/top_level.txt