Metadata-Version: 1.1
Name: evotum-cripto
Version: 1.0.1
Summary: eVotUM Cripto
Home-page: https://gitlab.com/eVotUM/Cripto-py
Author: André Baptista
Author-email: andre.baptista@devisefutures.com
License: GPL-3.0
Keywords: electronic vote crypto
Platform: UNKNOWN
Classifier: Development Status :: 5 - Production/Stable
Classifier: Topic :: Security :: Cryptography
Classifier: License :: OSI Approved :: GNU General Public License v3 (GPLv3)
